LICENSE
README.md
setup.py
akasa/__init__.py
akasa/module1.py
akasa/module2.py
akasa.egg-info/PKG-INFO
akasa.egg-info/SOURCES.txt
akasa.egg-info/dependency_links.txt
akasa.egg-info/top_level.txt