Metadata-Version: 2.1
Name: akasa
Version: 1.0.0
Summary: This is a cool package
Author: Bijay Das
Author-email: imbijaydas@gmail.com
License: GNU GENERAL PUBLIC LICENSE
License-File: LICENSE
